{"name": "박수지", "company": "공무원 (경상남도 진주시청)", "function": "일반행정", "years_at_reg": 6, "years_now": 8, "first_season": "24여름", "latest_season": "24여름", "total_count": 1, "has_4l": false, "seasons": [{"season": "24여름", "season_raw": "2024년 06-08월 여름시즌", "team": "영어리부팅", "team_normalized": "영어리부팅", "track": "Enrichment", "type": "첫등록", "motivation": "더 넓은 사회를 경험하고, 사람들을 만나 더 발전하고싶습니다.\n 지방에 거주하고 있어, 고민만 계속하다 이대로 참여못하면 후회할꺼같아서 신청합니다.\n 많이 부족하지만 열심히 배우고 적극적으로 임하겠습니다.", "ot_attended": null, "channel": "", "review_4l": null, "company": "공무원 (경상남도 진주시청)", "function": "일반행정", "years_at_reg": "6"}], "recommendations_26여름": null, "token": "24963941aa4cfeef"}