{"name": "이진주", "company": "씨네플레이", "function": "기자", "years_at_reg": 3, "years_now": 4, "first_season": "25여름", "latest_season": "25여름", "total_count": 1, "has_4l": false, "seasons": [{"season": "25여름", "season_raw": "2025년 06-08월 여름시즌", "team": "BX라이팅", "team_normalized": "BX라이팅", "track": "Enrichment", "type": "첫등록", "motivation": "기존의 쓰는 글이 아닌 새로운 분야의 글을 쓰고, 커리어확장을 위한 토대를 닦고 싶어서 신청하게되었습니다.", "ot_attended": null, "channel": "", "review_4l": null, "company": "씨네플레이", "function": "기자", "years_at_reg": "3"}], "recommendations_26여름": null, "current_season_report": null, "token": "2a698ac61cc5d031"}