{"name": "장수정", "company": "LG디스플레이", "function": "마케팅", "years_at_reg": 6, "years_now": 10, "first_season": "20가을", "latest_season": "22가을", "total_count": 2, "has_4l": false, "seasons": [{"season": "20가을", "season_raw": "2020년 09-11월 가을시즌", "team": "경영브릿지", "team_normalized": "경영브릿지", "track": "New Horizons", "type": "첫등록", "motivation": "내가 원하는 일을 찾는데 있어서 커뮤니티로부터 자극을 받기 위해", "ot_attended": null, "channel": "", "review_4l": null, "company": "LG디스플레이", "function": "마케팅", "years_at_reg": ""}, {"season": "22가을", "season_raw": "2022년 09-11월 가을시즌", "team": "강점차별화", "team_normalized": "강점차별화", "track": "Enrichment", "type": "재등록", "motivation": "자기계발", "ot_attended": null, "channel": "", "review_4l": null, "company": "LG디스플레이", "function": "", "years_at_reg": "6"}], "recommendations_26여름": {"picks": [{"team": "마케팅디깅", "reason": "LG디스플레이 마케팅 직무인데 거친 트랙이 모두 Enrichment·New Horizons였습니다. 마케터 관점을 넓히고 성과로 설득하는 법을 다루는 이 팀이 실무와 가장 잘 맞습니다.", "track": "Horizontal", "day_type": "주중", "headline": "마케터가 성과를 달성하고 숫자로 설득하는 법"}, {"team": "커리어캠프", "reason": "등록 동기가 '내가 원하는 일을 찾고 싶다'였습니다. Realignment 트랙은 아직 경험이 없어, 커리어 방향을 새로 설계하는 이 팀에서 자극을 받기 좋습니다.", "track": "Realignment", "day_type": "주중", "headline": ""}, {"team": "넘버앤센스", "reason": "마케팅 실무자로서 숫자로 설득하는 역량은 늘 필요합니다. Horizontal 트랙 경험이 없는 만큼 정량·정성 데이터를 함께 다루는 시각을 새로 얻기 좋습니다.", "track": "Horizontal", "day_type": "주중", "headline": "숫자 감각과 데이터 분석력을 기르기 위해 비즈니스의 맥락을 파악합니다"}], "generated_at": "2026-04-22T18:51:08.943562"}, "token": "3b990c3520598076"}