{"name": "권준혁", "company": "Na", "function": "서비스", "years_at_reg": 5, "years_now": 9, "first_season": "19여름", "latest_season": "22봄", "total_count": 2, "has_4l": false, "seasons": [{"season": "19여름", "season_raw": "2019년 06-08월 여름시즌", "team": "(경영) 경영브릿지-강남마스", "team_normalized": "경영브릿지", "track": "New Horizons", "type": "첫등록", "motivation": "토론을 통해 경영지식도 쌓고, 말하는 실력을 키우고자 등록하였습니다", "ot_attended": null, "channel": "", "review_4l": null, "company": "대신증권", "function": "서비스", "years_at_reg": ""}, {"season": "22봄", "season_raw": "2022년 03-05월 봄시즌", "team": "온라인전략", "team_normalized": "온라인전략", "track": "Horizontal", "type": "재등록", "motivation": "온라인 비즈니스에 관심이 있어서 등록하게 되었습니다.", "ot_attended": null, "channel": "", "review_4l": null, "company": "Na", "function": "", "years_at_reg": "5"}], "recommendations_26여름": {"picks": [{"team": "AI부사수", "reason": "온라인 비즈니스 관심과 실무 확장을 원하시니 AI를 부사수로 쓰는 법을 익히면 증권 서비스 직무에서 바로 써먹을 수 있습니다.", "track": "Enrichment", "day_type": "주중", "headline": "부사수 없이 홀로 모든 것을 완성해야 한다면", "product_url": "https://thehfk.org/shop_view?idx=232"}, {"team": "리더십첫줄", "reason": "2019년 경영브릿지 이후 경영지식과 말하기를 다시 원하시니 팀장 관점에서 자기 리더십 스타일을 토론으로 점검하기 좋습니다.", "track": "Vertical", "day_type": "주말", "headline": "신입 팀장은 실수와 깨달음을 반복하며 성장합니다", "product_url": "https://thehfk.org/shop_view?idx=50"}, {"team": "강점차별화", "reason": "두 번째 재등록이라 방향 점검이 필요한 시점입니다. 데이터 기반으로 자기 강점을 정리하면 다음 트랙 선택이 선명해집니다.", "track": "Enrichment", "day_type": "주말", "headline": "AI 시대에 가장 필요한 것은 나에 대한 체계적인 이해입니다", "product_url": "https://thehfk.org/shop_view?idx=51"}], "generated_at": "2026-04-22T18:51:08.918566"}, "current_season_report": null, "token": "41d97aa1589828f5"}