{"name": "오준호", "company": "RST Co., Ltd", "function": "총괄", "years_at_reg": 15, "years_now": 18, "first_season": "19겨울", "latest_season": "23봄", "total_count": 5, "has_4l": false, "seasons": [{"season": "19겨울", "season_raw": "2019년 12-02월 겨울시즌", "team": "(경영) 경영브릿지", "team_normalized": "경영브릿지", "track": "New Horizons", "type": "첫등록", "motivation": "지인의 추천", "ot_attended": null, "channel": "", "review_4l": null, "company": "RST", "function": "서비스", "years_at_reg": ""}, {"season": "20여름", "season_raw": "2020년 06-08월 여름시즌", "team": "사업기획툴", "team_normalized": "사업기획툴", "track": "Horizontal", "type": "재등록", "motivation": "좋아서!!", "ot_attended": null, "channel": "", "review_4l": null, "company": "", "function": "", "years_at_reg": ""}, {"season": "20겨울", "season_raw": "2020년 12-02월 겨울시즌", "team": "리더십첫줄", "team_normalized": "리더십첫줄", "track": "Vertical", "type": "재등록", "motivation": "나만의 리더쉽을 찾기 위해", "ot_attended": null, "channel": "", "review_4l": null, "company": "", "function": "", "years_at_reg": ""}, {"season": "22겨울", "season_raw": "2022년 12-02월 겨울시즌", "team": "서비스탄생", "team_normalized": "서비스탄생", "track": "Horizontal", "type": "재등록", "motivation": "서비스 개발에 대한 지식 습득", "ot_attended": null, "channel": "", "review_4l": null, "company": "RST Co., Ltd", "function": "총괄", "years_at_reg": "15"}, {"season": "23봄", "season_raw": "2023년 03-05월 봄시즌", "team": "인생첫카피", "team_normalized": "인생첫카피", "track": "Enrichment", "type": "재등록", "motivation": "마음을 사로잡는 제목을 만들고 싶어서~", "ot_attended": null, "channel": "", "review_4l": null, "company": "RST Co., Ltd", "function": "총괄", "years_at_reg": "15"}], "recommendations_26여름": {"picks": [{"team": "AI부사수", "reason": "서비스 개발 지식 습득이 동기인데, AI를 부사수로 써서 서비스 기획과 리서치를 혼자 굴려보는 경험이 잘 맞아 보입니다.", "track": "Enrichment", "day_type": "주중", "headline": "부사수 없이 홀로 모든 것을 완성해야 한다면", "product_url": "https://thehfk.org/shop_view?idx=232"}, {"team": "커리어캠프", "reason": "5시즌 동안 경영, 기획, 리더십, 카피까지 거쳤는데 이제 흩어진 경험을 커리어 전환 관점에서 재정렬할 시점으로 보입니다.", "track": "Realignment", "day_type": "주중", "headline": "", "product_url": "https://thehfk.org/shop_view?idx=63"}, {"team": "강점차별화", "reason": "서비스탄생, 인생첫카피 등 기획과 표현 트랙을 오래 했는데 자기 강점을 데이터로 정리하면 다음 방향이 또렷해질 겁니다.", "track": "Enrichment", "day_type": "주말", "headline": "AI 시대에 가장 필요한 것은 나에 대한 체계적인 이해입니다", "product_url": "https://thehfk.org/shop_view?idx=51"}], "generated_at": "2026-04-22T18:51:08.924682"}, "current_season_report": null, "token": "53c286fd461c8609"}