{"name": "윤소현", "company": "헤르츠", "function": "콘텐츠 매니저", "years_at_reg": 11, "years_now": 12, "first_season": "25겨울", "latest_season": "25겨울", "total_count": 1, "has_4l": true, "seasons": [{"season": "25겨울", "season_raw": "2025년 12-02월 겨울시즌", "team": "감각적기획", "team_normalized": "감각적기획", "track": "Horizontal", "type": "첫등록", "motivation": "블로그 마케팅부터 SNS까지 다양한 채널의 콘텐츠를 기획해왔는데요. 감각을 키우고 기획력을 뾰족하게 만드는 일에 대해 지속적인 관심을 가져왔어요. 좀 더 적극적으로 고민하고, 디벨롭해보고 싶어 지원합니다.", "ot_attended": null, "channel": "", "review_4l": {"rounds": [{"number": 3, "title": "3회차", "raw": "Liked: 포착하지 못한 일상의 디테일 포인트들을 이야기하고, 사우나붐에 대한 해외사례를 보는 즐거움이 있었습니다.\nLearned: 퍼플렉시티를 활용해서 SCAMPER 기법으로 아이데이션 하는 법\nLacked: 고객여정 완성지도 잘 준비해보겠습니다.\nLong for: 현재 맡고 있는 프로젝트에 적용해 보기"}]}, "company": "헤르츠", "function": "콘텐츠 매니저", "years_at_reg": "11"}], "recommendations_26여름": null, "current_season_report": null, "token": "77efa19cffe7b991"}