{"name": "허재필", "company": "주식회사 커피즈", "function": "영업", "years_at_reg": 5, "years_now": 6, "first_season": "25봄", "latest_season": "25여름", "total_count": 2, "has_4l": false, "seasons": [{"season": "25봄", "season_raw": "2025년 03-05월 봄시즌", "team": "경영에센셜", "team_normalized": "경영에센셜", "track": "New Horizons", "type": "첫등록", "motivation": "시야를 넓히고 싶고 새로운 자극을 느끼고자 신청합니다.", "ot_attended": null, "channel": "", "review_4l": null, "company": "주식회사 커피즈", "function": "영업", "years_at_reg": "5"}, {"season": "25여름", "season_raw": "2025년 06-08월 여름시즌", "team": "강점차별화", "team_normalized": "강점차별화", "track": "Enrichment", "type": "첫재등록", "motivation": "앞으로 성장하기 위해서 무엇을 준비해야하는지 배우고 느끼고자 신청합니다.", "ot_attended": null, "channel": "", "review_4l": null, "company": "주식회사 커피즈", "function": "영업", "years_at_reg": "5"}], "recommendations_26여름": {"picks": [{"team": "넘버앤센스", "reason": "영업 5년차로 숫자 보고가 일상일 텐데 아직 Horizontal 경험이 없습니다. 정량과 정성 데이터를 엮어 설득하는 법을 배우면 시야 확장 동기와 잘 맞습니다.", "track": "Horizontal", "day_type": "주중", "headline": "숫자 감각과 데이터 분석력을 기르기 위해 비즈니스의 맥락을 파악합니다"}, {"team": "마케팅디깅", "reason": "경영에센셜과 강점차별화로 자기 점검은 했으니 이번엔 영업 옆 동네인 마케터 시각을 볼 차례입니다. 성과와 판단 사이 고민에 새 자극이 됩니다.", "track": "Horizontal", "day_type": "주중", "headline": "마케터가 성과를 달성하고 숫자로 설득하는 법"}, {"team": "AI부사수", "reason": "4L에서 시간관리 부족을 꼽으셨습니다. 영업 반복 업무를 AI에 맡기는 법을 익히면 최근 Enrichment 흐름을 이어가며 실무 부담을 덜 수 있습니다.", "track": "Enrichment", "day_type": "주중", "headline": "부사수 없이 홀로 모든 것을 완성해야 한다면"}], "generated_at": "2026-04-22T13:52:20.013923"}, "token": "a1652ac102dd2655"}