{"name": "부해진", "company": "비공개", "function": "제조", "years_at_reg": null, "years_now": null, "first_season": "20봄", "latest_season": "20봄", "total_count": 1, "has_4l": false, "seasons": [{"season": "20봄", "season_raw": "2020년 03-05월 봄시즌", "team": "트렌드슈팅", "team_normalized": "트렌드슈팅", "track": "New Horizons", "type": "첫등록", "motivation": "트렌드에 대한 관심", "ot_attended": null, "channel": "직장인 스터디관련 검색/인스타그램", "review_4l": null, "company": "비공개", "function": "제조", "years_at_reg": ""}], "recommendations_26여름": null, "token": "a2e93b7590208282"}