{"name": "이찬희", "company": "집꾸미기", "function": "기획", "years_at_reg": null, "years_now": null, "first_season": "19가을", "latest_season": "19겨울", "total_count": 3, "has_4l": false, "seasons": [{"season": "19가을", "season_raw": "2019년 09-11월 가을시즌", "team": "(New_경영) 경영에센셜", "team_normalized": "경영에센셜", "track": "New Horizons", "type": "첫등록", "motivation": "경영공부", "ot_attended": null, "channel": "각종 SNS", "review_4l": null, "company": "집꾸미기", "function": "마케팅", "years_at_reg": ""}, {"season": "19가을", "season_raw": "2019년 09-11월 가을시즌", "team": "(경영) 경영브릿지-강남머큐리", "team_normalized": "경영브릿지", "track": "New Horizons", "type": "재등록", "motivation": "경영케이스 공유 및 네트워크", "ot_attended": null, "channel": "", "review_4l": null, "company": "집꾸미기", "function": "기획", "years_at_reg": ""}, {"season": "19겨울", "season_raw": "2019년 12-02월 겨울시즌", "team": "(New_경영) 전략가의일", "team_normalized": "전략가의일", "track": "Horizontal", "type": "재등록", "motivation": "전략 지식 배움", "ot_attended": null, "channel": "", "review_4l": null, "company": "", "function": "", "years_at_reg": ""}], "recommendations_26여름": {"picks": [{"team": "리더십첫줄", "reason": "경영브릿지와 전략가의일로 전략 시야를 키워오셨으니, 이제 거치지 않은 Vertical로 넘어가 마케팅 실무 리더로서 팀을 이끄는 역량을 준비하기 좋은 시점으로 보입니다.", "track": "Vertical", "day_type": "주말", "headline": "신입 팀장은 실수와 깨달음을 반복하며 성장합니다", "product_url": "https://thehfk.org/shop_view?idx=50"}, {"team": "AI부사수", "reason": "전략 지식과 네트워크를 찾으시는 마케터에게, 집꾸미기 실무에서 반복되는 작업을 AI로 덜어내고 기획에 더 집중할 수 있는 Enrichment 경험이 필요해 보입니다.", "track": "Enrichment", "day_type": "주중", "headline": "부사수 없이 홀로 모든 것을 완성해야 한다면", "product_url": "https://thehfk.org/shop_view?idx=232"}, {"team": "커리어캠프", "reason": "재등록 3회에 거친 트랙이 두 갈래뿐이라 방향 점검이 필요한 타이밍입니다. 전략 학습 동기를 커리어 재설계 관점에서 정리해보시길 권합니다.", "track": "Realignment", "day_type": "주중", "headline": "", "product_url": "https://thehfk.org/shop_view?idx=63"}], "generated_at": "2026-04-22T18:51:08.921867"}, "current_season_report": null, "token": "cbedb41b53b50a0b"}