{"name": "김종수", "company": "이노션", "function": "상품개발", "years_at_reg": 7, "years_now": 8, "first_season": "25겨울", "latest_season": "25겨울", "total_count": 1, "has_4l": true, "seasons": [{"season": "25겨울", "season_raw": "2025년 12-02월 겨울시즌", "team": "경영브릿지", "team_normalized": "경영브릿지", "track": "New Horizons", "type": "첫등록", "motivation": "다양한 이슈에 대한 깊이 있는 토론", "ot_attended": null, "channel": "", "review_4l": {"rounds": [{"number": 1, "title": "1회차.", "raw": "Liked 다양한 분야 분들의 이야기를 들을수 있어 좋았습니다\nLearned 분야에 따라 일에따라, 고민하시는\n분야가 이렇게나 다르다는 것을 느꼈습니다.\nLacked 새로운 관점과 모르는 분야에 대해 좀 더 알아보는 시간을 가져보려 합니다.\nLong for 오늘 접한 분야(산업군, 영역) 대해 2주간 경험해보고 찾아보려 합니다."}]}, "company": "이노션", "function": "상품개발", "years_at_reg": "7"}], "recommendations_26여름": null, "current_season_report": null, "token": "ccf42d4aaaae223e"}