{"name": "곽보미", "company": "P&G Korea", "function": "마케팅", "years_at_reg": null, "years_now": null, "first_season": "21봄", "latest_season": "21봄", "total_count": 1, "has_4l": false, "seasons": [{"season": "21봄", "season_raw": "2021년 03-05월 봄시즌", "team": "린스타트업", "team_normalized": "린스타트업", "track": "New Horizons", "type": "첫등록", "motivation": "스타트업 사업개발 쪽 이직을 고려하고 있어서 테마에 대해 기대가 큽니다! :)", "ot_attended": null, "channel": "직장동료의 경험으로 알게되었습니다.", "review_4l": null, "company": "P&G Korea", "function": "마케팅", "years_at_reg": ""}], "recommendations_26여름": null, "token": "d1d6b3af1dec6e1d"}