{"name": "최보윤", "company": "엘지전자(프리랜서)", "function": "손익분석 시스템 개발", "years_at_reg": 15, "years_now": 17, "first_season": "24가을", "latest_season": "24가을", "total_count": 1, "has_4l": false, "seasons": [{"season": "24가을", "season_raw": "2024년 09-11월 가을시즌", "team": "판매플래닝", "team_normalized": "판매플래닝", "track": null, "type": "첫등록", "motivation": "더욱 성장하고 성숙하는 사람이되기위해", "ot_attended": null, "channel": "", "review_4l": null, "company": "엘지전자(프리랜서)", "function": "손익분석 시스템 개발", "years_at_reg": "15"}], "recommendations_26여름": null, "token": "d24784a8f507809f"}