{"name": "권지현", "company": "씨티은행", "function": "", "years_at_reg": 7, "years_now": 11, "first_season": "22봄", "latest_season": "22여름", "total_count": 2, "has_4l": false, "seasons": [{"season": "22봄", "season_raw": "2022년 03-05월 봄시즌", "team": "써보는경험", "team_normalized": "써보는경험", "track": "New Horizons", "type": "첫등록", "motivation": "글을 쓴다 생각하면, 첫 문장의 첫 단어조차 어떻게 써야할지 막막하더라구요. 또, 다양한 주제가 있겠지만, 나를 알아가는 과정을 글로 남겨보고 싶습니다", "ot_attended": null, "channel": "", "review_4l": null, "company": "씨티은행", "function": "", "years_at_reg": "7"}, {"season": "22여름", "season_raw": "2022년 06-08월 여름시즌", "team": "스몰브랜드", "team_normalized": "스몰브랜드", "track": "New Horizons", "type": "재등록", "motivation": "외부에서 새로운 자극을 받고 싶어요!", "ot_attended": null, "channel": "", "review_4l": null, "company": "씨티은행", "function": "", "years_at_reg": "7"}], "recommendations_26여름": {"picks": [{"team": "커리어플랜", "reason": "3년 만의 복귀에 '새로운 자극'과 '나를 알아가는 글쓰기'를 원하셨습니다. 은행 7년차 시점에서 커리어를 다시 펼쳐보기 좋은 자리입니다.", "track": "Realignment", "day_type": "주중", "headline": "'제너럴'을 요구하는 세상에서 꽉 붙잡을 것과 새로 채워야 할 것들", "product_url": null}, {"team": "서울재발견", "reason": "과거 써보는경험·스몰브랜드에서 New Horizons만 두 번 밟으셨으니, 이번엔 Horizontal 시각으로 기획서 쓰는 감각을 붙여볼 타이밍입니다.", "track": "Horizontal", "day_type": "주중", "headline": "도쿄의 브랜드·공간·도시에서 내 업무에 가져올 기획 근육을", "product_url": "https://thehfk.org/shop_view?idx=207"}, {"team": "AI부사수", "reason": "씨티은행 7년차 실무에서 매일 돌아가는 AI 스킬을 손에 쥐면, 반복 업무가 줄고 새로운 자극 받을 여력이 생깁니다.", "track": "Enrichment", "day_type": "주중", "headline": "부사수 없이 일하는 사람을 위한 내 전용 AI 동료 만들기", "product_url": "https://thehfk.org/shop_view?idx=232"}], "generated_at": "2026-04-24T21:08:11.525547"}, "current_season_report": null, "token": "ea311698d083fe6f"}